littlefieldpy/Littlefield.py
littlefieldpy/__init__.py
littlefieldpy/model/CompletedJobs.py
littlefieldpy/model/Materials.py
littlefieldpy/model/Orders.py
littlefieldpy/model/Paths.py
littlefieldpy/model/Station.py
littlefieldpy/model/__init__.py
littlefieldpy-0.0.5.dist-info/LICENSE
littlefieldpy-0.0.5.dist-info/METADATA
littlefieldpy-0.0.5.dist-info/WHEEL
littlefieldpy-0.0.5.dist-info/top_level.txt
littlefieldpy-0.0.5.dist-info/RECORD
